[
  {
    "email": "isha.patel@example.com",
    "fullname": { "firstname": "Isha", "lastname": "Patel" },
    "age": 22,
    "gender": "Female",
    "region": "Surat",
    "interestCategory": ["Sports", "Fitness"],
    "persona": ["Budget Shopper"],
    "priceRange": "Budget_Friendly",
    "shoppingFrequency": "Weekly",
    "searchHistory": [{ "keyword": "racket" }, { "keyword": "shoes" }],
    "cart": [{ "productId": "P101", "quantity": 1 }],
    "transactionHistory": ["P101"]
  },
  {
    "email": "ravi.shah@example.com",
    "fullname": { "firstname": "Ravi", "lastname": "Shah" },
    "age": 28,
    "gender": "Male",
    "region": "Ahmedabad",
    "interestCategory": ["Home Essentials"],
    "persona": ["Mid_Range"],
    "priceRange": "Mid_Range",
    "shoppingFrequency": "Monthly",
    "searchHistory": [{ "keyword": "bottle" }],
    "cart": [],
    "transactionHistory": ["P105"]
  },
  {
    "email": "neha.doshi@example.com",
    "fullname": { "firstname": "Neha", "lastname": "Doshi" },
    "age": 30,
    "gender": "Female",
    "region": "Rajkot",
    "interestCategory": ["Electronics"],
    "persona": ["Premium"],
    "priceRange": "Premium",
    "shoppingFrequency": "Weekly",
    "searchHistory": [{ "keyword": "earbuds" }],
    "cart": [{ "productId": "P103", "quantity": 1 }],
    "transactionHistory": ["P103"]
  }
]
